ADVCALC/__init__.py
ADVCALC/calc.py
ADVCALC/cli.py
advcalc-67.2.4.dist-info/LICENSE
advcalc-67.2.4.dist-info/METADATA
advcalc-67.2.4.dist-info/WHEEL
advcalc-67.2.4.dist-info/entry_points.txt
advcalc-67.2.4.dist-info/top_level.txt
advcalc-67.2.4.dist-info/RECORD
