Metadata-Version: 2.1
Name: advcalc
Version: 67.2.4
Summary: Advanced Python Calculator With an API
Author: Zack
License: MIT
Keywords: python,calculator
License-File: LICENSE
Requires-Dist: setuptools >=61.0
